hyperllm/__init__.py
hyperllm/interface.py
hyperllm/providers/__init__.py
hyperllm/providers/anthropic_provider.py
hyperllm/providers/base.py
hyperllm/providers/cohere_provider.py
hyperllm/providers/custom_provider.py
hyperllm/providers/gemini_provider.py
hyperllm/providers/huggingface_provider.py
hyperllm/providers/ollama_provider.py
hyperllm/providers/openai_provider.py
hyperllm/utils/__init__.py
hyperllm/utils/cache.py
hyperllm/utils/exceptions.py
hyperllm/utils/interactive.py
hyperllm-1.0.1.dist-info/licenses/LICENSE
tests/__init__.py
tests/test_interface.py
tests/test_utils.py
tests/test_providers/__init__.py
tests/test_providers/test_anthropic.py
tests/test_providers/test_ollama.py
tests/test_providers/test_openai.py
hyperllm-1.0.1.dist-info/METADATA
hyperllm-1.0.1.dist-info/WHEEL
hyperllm-1.0.1.dist-info/top_level.txt
hyperllm-1.0.1.dist-info/RECORD
