Metadata-Version: 2.4
Name: hyperllm
Version: 1.0.1
Summary: A unified interface for multiple LLM providers with caching and interactive development mode to get massive cost savings.
Home-page: https://github.com/hyper-swe/hyperllm
Author: Swe
Author-email: swe@hyperswe.com
Project-URL: Bug Reports, https://github.com/hyper-swe/hyperllm/issues
Project-URL: Source, https://github.com/hyper-swe/hyperllm
Project-URL: Documentation, https://github.com/hyper-swe/hyperllm#readme
Keywords: llm,llmproxy,ai,openai,anthropic,claude,ollama,cost-saving,caching,interactive-mode,genai,hyper-llm
Classifier: Development Status :: 4 - Beta
Classifier: Intended Audience :: Developers
Classifier: License :: OSI Approved :: MIT License
Classifier: Operating System :: OS Independent
Classifier: Programming Language :: Python :: 3
Classifier: Programming Language :: Python :: 3.8
Classifier: Programming Language :: Python :: 3.9
Classifier: Programming Language :: Python :: 3.10
Classifier: Programming Language :: Python :: 3.11
Classifier: Programming Language :: Python :: 3.12
Classifier: Topic :: Software Development :: Libraries :: Python Modules
Classifier: Topic :: Scientific/Engineering :: Artificial Intelligence
Requires-Python: >=3.8
License-File: LICENSE
Requires-Dist: requests>=2.25.0
Provides-Extra: openai
Requires-Dist: openai>=1.0.0; extra == "openai"
Provides-Extra: anthropic
Requires-Dist: anthropic>=0.64.0; extra == "anthropic"
Provides-Extra: clipboard
Requires-Dist: pyperclip>=1.8.0; extra == "clipboard"
Provides-Extra: all
Requires-Dist: openai>=1.0.0; extra == "all"
Requires-Dist: anthropic>=0.64.0; extra == "all"
Requires-Dist: pyperclip>=1.8.0; extra == "all"
Dynamic: author
Dynamic: author-email
Dynamic: classifier
Dynamic: description
Dynamic: description-content-type
Dynamic: home-page
Dynamic: keywords
Dynamic: license-file
Dynamic: project-url
Dynamic: provides-extra
Dynamic: requires-dist
Dynamic: requires-python
Dynamic: summary
